[
    {
        "name": "Strzyżenie brody",
        "price": 40.00,
        "time": 30
    },
    {
        "name": "Odsiwianie",
        "price": 60.00,
        "time": 30
    },
    {
        "name": "Pielęgnacja brody",
        "price": 50.00,
        "time": 20
    },
    {
        "name": "Golenie",
        "price": 60.00,
        "time": 45
    },
    {
        "name": "Farbowanie brody",
        "price": 80.00,
        "time": 60
    },
    {
        "name": "Golenie brzytwą",
        "price": 60.00,
        "time": 40
    },
    {
        "name": "Stylizacja brody",
        "price": 50.00,
        "time": 30

    },
    {
        "name": "Golenie brody",
        "price": 60.00,
        "time": 40

    },
    {
        "name": "Golenie głowy",
        "price": 60.00,
        "time": 40
    }
]